Metadata-Version: 2.1
Name: waycheck
Version: 0.0.1
Summary: A lightweight Python type checker. Designed with the developer in mind.
Home-page: https://github.com/ableinc/waycheck
Author: AbleInc - Jaylen Douglas
Author-email: douglas.jaylen@gmail.com
License: UNKNOWN
Keywords: waycheck,typechecker,type,check,assertion,assertion check,python types,ableinc,python type check,python type checker,python decorator,decorator,decorator class,type check decorator
Platform: UNKNOWN
Classifier: Programming Language :: Python :: 3.5
Classifier: Programming Language :: Python :: 3.6
Classifier: Programming Language :: Python :: 3.7
Classifier: Programming Language :: Python :: 3.8
Classifier: Programming Language :: Python :: 3 :: Only
Classifier: License :: OSI Approved :: MIT License
Classifier: Operating System :: OS Independent
